raiden_synapse_modules/__init__.py
raiden_synapse_modules/admin_user_auth_provider.py
raiden_synapse_modules/eth_auth_provider.py
raiden_synapse_modules/federation_whitelist_reloader.py
raiden_synapse_modules/presence_router/__init__.py
raiden_synapse_modules/presence_router/blockchain_support.py
raiden_synapse_modules/presence_router/pfs.py
raiden_synapse_modules-0.1.4.dist-info/LICENSE
raiden_synapse_modules-0.1.4.dist-info/WHEEL
raiden_synapse_modules-0.1.4.dist-info/METADATA
raiden_synapse_modules-0.1.4.dist-info/RECORD
