Metadata-Version: 2.1
Name: raiden-synapse-modules
Version: 0.1.4
Summary: synapse modules for the Raiden network
License: MIT
Keywords: raiden,raiden-network,synapse,matrix
Author: Brainbot Labs Est.
Author-email: contact@brainbot.li
Requires-Python: >=3.9,<4.0
Classifier: License :: OSI Approved :: MIT License
Classifier: Programming Language :: Python :: 3
Classifier: Programming Language :: Python :: 3.10
Classifier: Programming Language :: Python :: 3.9
Requires-Dist: coincurve (>=15.0.0,<16.0.0)
Requires-Dist: raiden-contracts (>=0.50.1,<0.51.0)
